logging_with_context/__init__.py
logging_with_context/adapters.py
logging_with_context/filters.py
logging_with_context/formatters.py
logging_with_context/global_context.py
logging_with_context/py.typed
logging_with_context-0.2.0.dist-info/METADATA
logging_with_context-0.2.0.dist-info/WHEEL
logging_with_context-0.2.0.dist-info/licenses/LICENSE
logging_with_context-0.2.0.dist-info/RECORD
