Metadata-Version: 2.4
Name: logging-with-context
Version: 0.2.0
Summary: Python library to add context to logging messages
Author-email: David Caro <terseus@fastmail.com>
License-Expression: MIT
License-File: LICENSE
Requires-Python: >=3.9
